langchain_groq/__init__.py
langchain_groq/chat_models.py
langchain_groq/py.typed
gigachain_groq-0.1.9.dist-info/LICENSE
gigachain_groq-0.1.9.dist-info/METADATA
gigachain_groq-0.1.9.dist-info/WHEEL
gigachain_groq-0.1.9.dist-info/RECORD
